cocommit/__init__.py
cocommit/cli_ui.py
cocommit/cocommit.py
cocommit/commit_amend.py
cocommit/dogs_vs_cats.py
cocommit/git_utils.py
cocommit/llm_caller.py
cocommit/llm_prompts/prompt.llm
cocommit/llm_prompts/test_prompt.llm
cocommit/parser/__init__.py
cocommit/parser/llm_reply.py
cocommit/parser/response_utils.py
cocommit/prompt_utils.py
cocommit/shortcuts.py
cocommit-1.0.0.dist-info/LICENSE.txt
cocommit-1.0.0.dist-info/METADATA
cocommit-1.0.0.dist-info/WHEEL
cocommit-1.0.0.dist-info/entry_points.txt
cocommit-1.0.0.dist-info/RECORD
