Metadata-Version: 2.3
Name: cocommit
Version: 1.0.0
Summary: This command-line GIT copilot analyzes your last commit and leverages an LLM of your choice to enhance it.
License: MIT
Author: Andrew Romanenco
Author-email: andrew@romanenco.com
Requires-Python: >=3.9,<4.0
Classifier: Development Status :: 5 - Production/Stable
Classifier: Environment :: Console
Classifier: Intended Audience :: Developers
Classifier: Topic :: Software Development :: Version Control :: Git
Classifier: Topic :: Utilities
Classifier: Programming Language :: Python :: 3.9
Classifier: Programming Language :: Python :: 3.10
Classifier: Programming Language :: Python :: 3.11
Classifier: Programming Language :: Python :: 3.12
Classifier: Programming Language :: Python :: 3.13
Requires-Dist: click (>=8.1.8,<9.0.0)
Requires-Dist: gitpython (>=3.1.44,<4.0.0)
Requires-Dist: langchain[aws] (>=0.3.21,<0.4.0)
Project-URL: Homepage, https://github.com/andrewromanenco/cocommit
Project-URL: Source, https://github.com/andrewromanenco/cocommit
